{
  "metrics": {
    "nationale": {
      "nb_orgas": 12,
      "nb_datasets": 169,
      "nb_resources": 446
    },
    "autre": {
      "nb_orgas": 20,
      "nb_datasets": 331,
      "nb_resources": 1601
    },
    "EPCI": {
      "nb_orgas": 20,
      "nb_datasets": 324,
      "nb_resources": 752
    },
    "communale": {
      "nb_orgas": 4,
      "nb_datasets": 243,
      "nb_resources": 496
    },
    "d\u00e9partementale": {
      "nb_orgas": 1,
      "nb_datasets": 33,
      "nb_resources": 144
    },
    "r\u00e9gionale": {
      "nb_orgas": 7,
      "nb_datasets": 55,
      "nb_resources": 226
    },
    "general": {
      "nb_orgas": 64,
      "nb_datasets": 1155,
      "nb_resources": 3665
    }
  },
  "formats": {
    "general": {
      "csv": 1504,
      "json": 406,
      "nc": 250,
      "xls": 64,
      "bin": 18,
      "kmz": 47,
      "ods": 61,
      "zip": 164,
      "xml": 62,
      "pdf": 67,
      "html": 7,
      "kml": 56,
      "geo+json": 1,
      "txt": 55,
      "geojson": 144,
      "docx": 1,
      "shp": 185,
      "jpe": 20,
      "api": 13,
      "xlsx": 31,
      "wfs": 166,
      "wms": 213,
      "ms-excel": 4,
      "sheet": 3,
      "rar": 17,
      "tiff": 1,
      "wcs": 1,
      "dxf": 7,
      "png": 1,
      "tif": 2,
      "7z": 14,
      "gtfs": 40,
      "other": 1,
      "netex": 36,
      "open data gironde num\u00e9rique": 3
    },
    "nationale": {
      "csv": 217,
      "json": 29,
      "txt": 55,
      "pdf": 28,
      "zip": 53,
      "xml": 17,
      "geojson": 12,
      "ods": 17,
      "xlsx": 17,
      "shp": 1
    },
    "autre": {
      "nc": 105,
      "csv": 749,
      "xls": 9,
      "bin": 18,
      "kmz": 10,
      "ods": 3,
      "zip": 93,
      "xml": 30,
      "pdf": 18,
      "html": 7,
      "kml": 15,
      "geo+json": 1,
      "wfs": 166,
      "wms": 161,
      "ms-excel": 4,
      "json": 91,
      "sheet": 3,
      "rar": 17,
      "tiff": 1,
      "wcs": 1,
      "gtfs": 36,
      "netex": 36,
      "shp": 13,
      "geojson": 10,
      "open data gironde num\u00e9rique": 3,
      "xlsx": 1
    },
    "EPCI": {
      "csv": 207,
      "xls": 55,
      "nc": 145,
      "kmz": 10,
      "json": 138,
      "geojson": 52,
      "zip": 17,
      "docx": 1,
      "pdf": 8,
      "ods": 41,
      "shp": 49,
      "xml": 2,
      "kml": 3,
      "gtfs": 4,
      "other": 1,
      "wms": 19
    },
    "communale": {
      "shp": 13,
      "json": 35,
      "csv": 266,
      "api": 13,
      "xlsx": 13,
      "xml": 13,
      "geojson": 70,
      "kmz": 27,
      "kml": 38,
      "dxf": 7,
      "png": 1
    },
    "d\u00e9partementale": {
      "json": 56,
      "csv": 33,
      "shp": 23,
      "pdf": 12,
      "jpe": 20
    },
    "r\u00e9gionale": {
      "json": 57,
      "csv": 32,
      "wms": 33,
      "tif": 2,
      "7z": 14,
      "shp": 86,
      "zip": 1,
      "pdf": 1
    }
  },
  "timings": {
    "reuse": [],
    "datasets": [
      1626071270,
      1626069820,
      1626069820,
      1626069819,
      1626069819,
      1626069819,
      1626069819,
      1626069819,
      1626069819,
      1626069819,
      1626069655,
      1626069655,
      1626069655,
      1626069655,
      1626069655,
      1626069655,
      1626069655,
      1626069655,
      1626069655,
      1626069655,
      1626069654,
      1626069654,
      1626069654,
      1626069654,
      1626069654,
      1626069654,
      1626069654,
      1626069654,
      1626069654,
      1626069654,
      1626069654,
      1626069654,
      1626069654,
      1626069654,
      1626069654,
      1626069654,
      1626069654,
      1626069654,
      1626069654,
      1626069654,
      1626069654,
      1626069654,
      1626069654,
      1626069654,
      1626069654,
      1626069654,
      1626069654,
      1626069654,
      1626069654,
      1626069654,
      1626069654,
      1626069654,
      1626069654,
      1626069654,
      1626069654,
      1626069654,
      1626069654,
      1626069654,
      1626069654,
      1626069654,
      1626069654,
      1626069654,
      1626069654,
      1626069654,
      1626069654,
      1626069653,
      1626069653,
      1626069653,
      1626069653,
      1626069653,
      1626069653,
      1626069653,
      1626069653,
      1626069653,
      1626069653,
      1626069653,
      1626069653,
      1626069653,
      1626069653,
      1626069653,
      1626069653,
      1626069653,
      1626069653,
      1626069653,
      1626069653,
      1626069653,
      1626069653,
      1626069653,
      1626069653,
      1626069653,
      1626069653,
      1626069653,
      1626069653,
      1626069653,
      1626069653,
      1626069653,
      1626069653,
      1626069653,
      1626069653,
      1626069653,
      1626069653,
      1626069653,
      1626069653,
      1626069653,
      1626069653,
      1626069653,
      1626069653,
      1626069653,
      1626069653,
      1626069653,
      1626069653,
      1626069653,
      1626069653,
      1626069653,
      1626069653,
      1626069653,
      1626069653,
      1626069653,
      1626069653,
      1626069653,
      1626069653,
      1626069653,
      1626069653,
      1626069653,
      1626069652,
      1626069652,
      1626069652,
      1626069652,
      1626069652,
      1626069652,
      1626069652,
      1626069652,
      1626069652,
      1626069652,
      1626069652,
      1626069652,
      1626069652,
      1626069652,
      1626069652,
      1626069652,
      1626069652,
      1626069652,
      1626069652,
      1626069652,
      1626069652,
      1626069652,
      1626069652,
      1626069652,
      1626069652,
      1626069652,
      1626069652,
      1626069652,
      1626069652,
      1626069652,
      1626069652,
      1626069652,
      1626069652,
      1626069652,
      1626069652,
      1626069652,
      1626069651,
      1626069651,
      1626069651,
      1626069651,
      1626069651,
      1626069651,
      1626069651,
      1626069651,
      1626069651,
      1626069651,
      1626069651,
      1626069651,
      1626069651,
      1626069651,
      1626069651,
      1626069651,
      1626069651,
      1626069651,
      1626069651,
      1626069651,
      1626069651,
      1626069651,
      1626069651,
      1626069651,
      1626069651,
      1626069651,
      1626069651,
      1626069651,
      1626069651,
      1626069651,
      1626069651,
      1626069651,
      1626069651,
      1626069651,
      1626069651,
      1626069651,
      1626069651,
      1626069651,
      1626069651,
      1626069651,
      1626069651,
      1626069651,
      1626069651,
      1626069651,
      1626069651,
      1626069651,
      1626069651,
      1626069651,
      1626069651,
      1626069651,
      1626069651,
      1626069651,
      1626069651,
      1626069651,
      1626069651,
      1626069651,
      1626069651,
      1626069651,
      1626069651,
      1626069651,
      1626069651,
      1626069651,
      1626069651,
      1626069651,
      1626069650,
      1626069650,
      1626069650,
      1626069650,
      1626069650,
      1626069650,
      1626069650,
      1626069650,
      1626069650,
      1626069650,
      1626069650,
      1626069650,
      1626069650,
      1626069650,
      1626069650,
      1626069650,
      1626069650,
      1626069650,
      1626069650,
      1626069650,
      1626069650,
      1626069650,
      1626069650,
      1626069650,
      1626069650,
      1626069643,
      1626069642,
      1626069642,
      1626069640,
      1626069625,
      1626069625,
      1626069625,
      1626069625,
      1626069625,
      1626069625,
      1626069624,
      1626069624,
      1626069624,
      1626069623,
      1626069623,
      1626069623,
      1626069623,
      1626069623,
      1626069623,
      1626069622,
      1626069622,
      1626069622,
      1626069622,
      1626069622,
      1626069621,
      1626069621,
      1626069621,
      1626069621,
      1626069621,
      1626069621,
      1626069620,
      1626069620,
      1626069620,
      1626069620,
      1626069620,
      1626069620,
      1626069620,
      1626069620,
      1626069620,
      1626069620,
      1626069620,
      1626069620,
      1626069620,
      1626069620,
      1626069619,
      1626069619,
      1626069619,
      1626069619,
      1626069619,
      1626069619,
      1626069619,
      1626069619,
      1626069619,
      1626069619,
      1626069618,
      1626069618,
      1626069618,
      1626069618,
      1626069618,
      1626069618,
      1626069618,
      1626069618,
      1626069618,
      1626069618,
      1626069618,
      1626069618,
      1626069618,
      1626069618,
      1626069618,
      1626069618,
      1626069618,
      1626069618,
      1626069618,
      1626069618,
      1626069618,
      1626069618,
      1626069618,
      1626069618,
      1626069618,
      1626069617,
      1626069617,
      1626069617,
      1626069617,
      1626069617,
      1626069617,
      1626069617,
      1626069617,
      1626069617,
      1626069617,
      1626069617,
      1626069617,
      1626069617,
      1626069617,
      1626069617,
      1626069617,
      1626069617,
      1626069617,
      1626069617,
      1626069617,
      1626069617,
      1626069617,
      1626069617,
      1626069616,
      1626069616,
      1626069616,
      1626069616,
      1626069616,
      1626069616,
      1626069616,
      1626069615,
      1626069615,
      1626069615,
      1626069615,
      1626069615,
      1626069615,
      1626069615,
      1626069615,
      1626069615,
      1626069615,
      1626069615,
      1626069615,
      1626069615,
      1626069615,
      1626069615,
      1626069614,
      1626069614,
      1626069614,
      1626069614,
      1626069614,
      1626069614,
      1626069614,
      1626069614,
      1626069614,
      1626069614,
      1626069614,
      1626069614,
      1626069614,
      1626069613,
      1626069613,
      1626069613,
      1626069613,
      1626069613,
      1626069613,
      1626069613,
      1626069613,
      1626069613,
      1626069613,
      1626069613,
      1626069613,
      1626069613,
      1626069613,
      1626069613,
      1626069613,
      1626069613,
      1626069613,
      1626069613,
      1626069613,
      1626069613,
      1626069613,
      1626069613,
      1626066038,
      1626066036,
      1626066035,
      1626066034,
      1626066024,
      1626066024,
      1626066023,
      1626066023,
      1626066023,
      1626066022,
      1626066022,
      1626066022,
      1626066022,
      1626066022,
      1626066022,
      1626066022,
      1626066022,
      1626066021,
      1626066021,
      1626066021,
      1626066020,
      1626066020,
      1626066020,
      1626066020,
      1626066020,
      1626066020,
      1626066020,
      1626066019,
      1626066019,
      1626066019,
      1626066019,
      1626066019,
      1626066019,
      1626066019,
      1626066019,
      1626066019,
      1626066019,
      1626066018,
      1626066018,
      1626066018,
      1626066018,
      1626066018,
      1626066017,
      1626066017,
      1626066017,
      1626066017,
      1626066017,
      1626066017,
      1626066017,
      1626066016,
      1626066016,
      1626066016,
      1626066016,
      1626066016,
      1626066016,
      1626066016,
      1626066016,
      1626066016,
      1626066016,
      1626066015,
      1626066015,
      1626066015,
      1626066015,
      1626066014,
      1626066014,
      1626066014,
      1626066014,
      1626066013,
      1626066013,
      1626066013,
      1626066012,
      1626066012,
      1626066012,
      1626066012,
      1626066012,
      1626066012,
      1626066012,
      1626066012,
      1626066012,
      1626066012,
      1626066012,
      1626066012,
      1626066011,
      1626066011,
      1626066011,
      1626066011,
      1626066011,
      1626066011,
      1626066010,
      1626066010,
      1626066010,
      1626066010,
      1626066010,
      1626066010,
      1626066010,
      1626066010,
      1626066010,
      1626066010,
      1626066010,
      1626066010,
      1626066010,
      1626066010,
      1626066010,
      1626066010,
      1626066010,
      1626066010,
      1626066009,
      1626066009,
      1626066009,
      1626066009,
      1626066009,
      1626066009,
      1626066009,
      1626066009,
      1626066009,
      1626066009,
      1626066009,
      1626066009,
      1626066009,
      1626066009,
      1626066009,
      1626066009,
      1626066009,
      1626066009,
      1626066009,
      1626066009,
      1626066009,
      1626066009,
      1626066009,
      1626066009,
      1626066009,
      1626066009,
      1626066009,
      1626066009,
      1626066009,
      1626066009,
      1626066009,
      1626066009,
      1626066009,
      1626066009,
      1626066009,
      1626066009,
      1626066009,
      1626066009,
      1626066009,
      1626066009,
      1626066009,
      1626066009,
      1626066009,
      1626066009,
      1626066009,
      1626066009,
      1626066009,
      1626066009,
      1626066009,
      1626066009,
      1626066009,
      1626066009,
      1626066009,
      1626066009,
      1626066009,
      1626066009,
      1626066009,
      1626066009,
      1626066009,
      1626066009,
      1626066009,
      1626066009,
      1626066009,
      1626066009,
      1626066009,
      1626066009,
      1626066009,
      1626066009,
      1626066009,
      1626066009,
      1626066009,
      1626066009,
      1626066009,
      1626066009,
      1626066009,
      1626066009,
      1626066009,
      1626066009,
      1626066009,
      1626066009,
      1626066009,
      1626066009,
      1626066009,
      1626066009,
      1626066009,
      1626066009,
      1626066009,
      1626066009,
      1626066009,
      1626066009,
      1626066009,
      1626066009,
      1626066009,
      1626066009,
      1626066009,
      1626066009,
      1626066009,
      1626066009,
      1626066009,
      1626066009,
      1626066009,
      1626066009,
      1626066009,
      1626066009,
      1626066009,
      1626066009,
      1626066009,
      1626066009,
      1626066009,
      1626066009,
      1626066009,
      1626066009,
      1626066009,
      1626066009,
      1626066009,
      1626066009,
      1626066009,
      1626066008,
      1626066008,
      1626066008,
      1626066008,
      1626066008,
      1626066008,
      1626066007,
      1626066007,
      1626066007,
      1626066007,
      1626066007,
      1626066007,
      1626066007,
      1626066007,
      1626066007,
      1626066007,
      1626066007,
      1626066007,
      1626066006,
      1626066006,
      1626066006,
      1626066006,
      1626066006,
      1626066006,
      1626066006,
      1626066006,
      1626066006,
      1626066006,
      1626066006,
      1626066006,
      1626066006,
      1626066005,
      1626066005,
      1626066005,
      1626066005,
      1626066005,
      1626066005,
      1626066005,
      1626066005,
      1626066005,
      1626066005,
      1626066004,
      1626066004,
      1626066004,
      1626066004,
      1626066004,
      1626066004,
      1626066004,
      1626066004,
      1626066003,
      1626066003,
      1626066003,
      1626066003,
      1626066003,
      1626066003,
      1626066003,
      1626066003,
      1626066002,
      1626066002,
      1626066002,
      1626066002,
      1626066002,
      1626066002,
      1626066002,
      1626066002,
      1626066002,
      1626066002,
      1626066002,
      1626066002,
      1626066002,
      1626066001,
      1626066001,
      1626066001,
      1626066001,
      1626066001,
      1626066001,
      1626066001,
      1626066001,
      1626066001,
      1626066001,
      1626066001,
      1626066001,
      1626062643,
      1626062643,
      1626062643,
      1626062643,
      1626062526,
      1626062526,
      1626062526,
      1626062526,
      1626062494,
      1626062494,
      1626062491,
      1626062491,
      1626062484,
      1626062474,
      1626062474,
      1626062473,
      1626062473,
      1626062469,
      1626062469,
      1626062465,
      1626062465,
      1626062464,
      1626062464,
      1626062413,
      1626062413,
      1626062413,
      1626062413,
      1626062410,
      1626062410,
      1626062410,
      1626062410,
      1626062404,
      1626062404,
      1626062404,
      1626062404,
      1626062373,
      1626062373,
      1626062373,
      1626062373,
      1626061898,
      1626061879,
      1626061854,
      1626061825,
      1626061793,
      1626061753,
      1626061724,
      1626061687,
      1626061665,
      1626061665,
      1626061665,
      1626061665,
      1626061663,
      1626061663,
      1626061663,
      1626061663,
      1626061662,
      1626061662,
      1626061662,
      1626061662,
      1626061662,
      1626061662,
      1626061661,
      1626061660,
      1626061660,
      1626061659,
      1626061659,
      1626061659,
      1626061659,
      1626061659,
      1626061659,
      1626061659,
      1626061659,
      1626061657,
      1626061657,
      1626061656,
      1626061656,
      1626061656,
      1626061656,
      1626061656,
      1626061656,
      1626061656,
      1626061656,
      1626061654,
      1626061654,
      1626061653,
      1626061653,
      1626061653,
      1626061653,
      1626061653,
      1626061653,
      1626061653,
      1626061653,
      1626061637,
      1626061634,
      1626061634,
      1626061634,
      1626061634,
      1626061633,
      1626061633,
      1626061633,
      1626061633,
      1626061625,
      1626061625,
      1626061625,
      1626061625,
      1626061625,
      1626061625,
      1626061625,
      1626061625,
      1626061624,
      1626061624,
      1626061622,
      1626061622,
      1626061622,
      1626061622,
      1626061622,
      1626061622,
      1626061617,
      1626061617,
      1626061617,
      1626061617,
      1626061617,
      1626061617,
      1626061607,
      1626061580,
      1626061555,
      1626061528,
      1626061496,
      1626061469,
      1626061445,
      1626061414,
      1626061386,
      1626061353,
      1626061330,
      1626061266,
      1626061235,
      1626060700,
      1626060699,
      1626059711,
      1626059711,
      1626059711,
      1626059711,
      1626059532,
      1626059532,
      1626059532,
      1626059532,
      1626059470,
      1626059470,
      1626059470,
      1626059470,
      1626059411,
      1626059411,
      1626059411,
      1626059411,
      1626058890,
      1626058890,
      1626058854,
      1626058854,
      1626058803,
      1626058803,
      1626058803,
      1626058803,
      1626058748,
      1626058748,
      1626058748,
      1626058748,
      1626056468,
      1626056468,
      1626056110,
      1626056110,
      1626056110,
      1626056110,
      1626055914,
      1626055914,
      1626055914,
      1626055914,
      1626055914,
      1626055914,
      1626055914,
      1626055914,
      1626055914,
      1626055914,
      1626055914,
      1626055914,
      1626055914,
      1626055914,
      1626055914,
      1626055914,
      1626055914,
      1626055914,
      1626055913,
      1626055913,
      1626055913,
      1626055913,
      1626055913,
      1626055913,
      1626055913,
      1626055913,
      1626055913,
      1626055913,
      1626055913,
      1626055913,
      1626055913,
      1626055913,
      1626055913,
      1626055913,
      1626055913,
      1626055913,
      1626055913,
      1626055913,
      1626055913,
      1626055913,
      1626055913,
      1626055913,
      1626055913,
      1626055913,
      1626055913,
      1626055913,
      1626055913,
      1626055913,
      1626055900,
      1626055900,
      1626055900,
      1626055900,
      1626055900,
      1626055900,
      1626055900,
      1626055899,
      1626055899,
      1626055899,
      1626055899,
      1626055899,
      1626055899,
      1626055899,
      1626055899,
      1626055899,
      1626055899,
      1626055899,
      1626055899,
      1626055899,
      1626055899,
      1626055899,
      1626055899,
      1626055899,
      1626055899,
      1626055899,
      1626055899,
      1626055899,
      1626055899,
      1626055899,
      1626055899,
      1626055899,
      1626055899,
      1626055899,
      1626055898,
      1626055898,
      1626055898,
      1626055898,
      1626055898,
      1626055898,
      1626055898,
      1626055898,
      1626055898,
      1626055898,
      1626055898,
      1626055898,
      1626055898,
      1626055898,
      1626055898,
      1626055898,
      1626055898,
      1626055898,
      1626055898,
      1626055898,
      1626055898,
      1626055898,
      1626055898,
      1626055898,
      1626055898,
      1626055898,
      1626055898,
      1626055898,
      1626055898,
      1626055898,
      1626055898,
      1626055898,
      1626055898,
      1626055898,
      1626055898,
      1626055898,
      1626055898,
      1626055898,
      1626055898,
      1626055898,
      1626055898,
      1626055898,
      1626055898,
      1626055898,
      1626055898,
      1626055898,
      1626055898,
      1626055898,
      1626055898,
      1626055898,
      1626055898,
      1626055898,
      1626055898,
      1626055898,
      1626055898,
      1626055898,
      1626055897,
      1626055897,
      1626055897,
      1626055897,
      1626055897,
      1626055897,
      1626055897,
      1626055897,
      1626055897,
      1626055897,
      1626055897,
      1626055897,
      1626055897,
      1626055897,
      1626055897,
      1626055897,
      1626055897,
      1626055897,
      1626055897,
      1626055897,
      1626055897,
      1626055897,
      1626055897,
      1626055897,
      1626055897,
      1626055897,
      1626055897,
      1626055897,
      1626055897,
      1626055896,
      1626055896,
      1626055896,
      1626055896,
      1626055896,
      1626055896,
      1626055896,
      1626055896,
      1626055896,
      1626055896,
      1626055896,
      1626055896,
      1626055896,
      1626055896,
      1626055896,
      1626055896,
      1626055896,
      1626055896,
      1626055896,
      1626055896,
      1626055896,
      1626055896,
      1626055896,
      1626055896,
      1626055896,
      1626055896,
      1626055895,
      1626055895,
      1626055895,
      1626055895,
      1626055895,
      1626055895,
      1626055895,
      1626055895,
      1626055895,
      1626055895,
      1626055895,
      1626055895,
      1626055895,
      1626055895,
      1626055895,
      1626055895,
      1626055895,
      1626055895,
      1626055895,
      1626055895,
      1626055895,
      1626055895,
      1626055895,
      1626055894,
      1626055894,
      1626055894,
      1626055894,
      1626055894,
      1626055894,
      1626055894,
      1626055894,
      1626055894,
      1626055894,
      1626055894,
      1626055894,
      1626055894,
      1626055894,
      1626055894,
      1626055894,
      1626055894,
      1626055894,
      1626055894,
      1626055894,
      1626055894,
      1626055894,
      1626055894,
      1626055894,
      1626055894,
      1626055894,
      1626055894,
      1626055894,
      1626055894,
      1626055894,
      1626055894,
      1626055894,
      1626055894,
      1626055893,
      1626055893,
      1626055893,
      1626055893,
      1626055893,
      1626055893,
      1626055893,
      1626055893,
      1626055893,
      1626055893,
      1626055893,
      1626055893,
      1626055893,
      1626055893,
      1626055892,
      1626055892,
      1626055892,
      1626055892,
      1626055892,
      1626055892,
      1626055892,
      1626055890,
      1626055890,
      1626055890,
      1626055869,
      1626055869,
      1626055869,
      1626055869,
      1626055869,
      1626055869,
      1626055869,
      1626055869,
      1626055869,
      1626055869,
      1626055868,
      1626055868,
      1626055868,
      1626055868,
      1626055868,
      1626055868,
      1626055868,
      1626055868,
      1626055868,
      1626055868,
      1626055868,
      1626055868,
      1626055868,
      1626055868,
      1626055868,
      1626055868,
      1626055868,
      1626055868,
      1626055868,
      1626055868,
      1626055868,
      1626055868,
      1626055868,
      1626055868,
      1626055868,
      1626055868,
      1626055868,
      1626055868,
      1626055868,
      1626055868,
      1626055868,
      1626055868,
      1626055868,
      1626055868,
      1626055868,
      1626055868,
      1626055868,
      1626055868,
      1626055868,
      1626055868,
      1626055868,
      1626055868,
      1626055868,
      1626055868,
      1626055868,
      1626055868,
      1626055868,
      1626055868,
      1626055868,
      1626055868,
      1626055868,
      1626055868,
      1626055868,
      1626055868,
      1626055868,
      1626055868,
      1626055868,
      1626055868,
      1626055868,
      1626055868,
      1626055868,
      1626055868,
      1626055868,
      1626055868,
      1626055868,
      1626055868,
      1626055868,
      1626055868,
      1626055868,
      1626055868,
      1626055868,
      1626055868,
      1626055868,
      1626055868,
      1626055868,
      1626055868,
      1626055868,
      1626055868,
      1626055868,
      1626055868,
      1626055868,
      1626055868,
      1626055868,
      1626055868,
      1626055868,
      1626055868,
      1626055868,
      1626055868,
      1626055868,
      1626055868,
      1626055868,
      1626055868,
      1626055868,
      1626055868,
      1626055868,
      1626055868,
      1626055868,
      1626055868,
      1626055868,
      1626055868,
      1626055868,
      1626055868,
      1626055868,
      1626055868,
      1626055868,
      1626055868,
      1626055868,
      1626055868,
      1626055868,
      1626055868,
      1626055868,
      1626055868,
      1626055868,
      1626055868,
      1626055868,
      1626055868,
      1626055868,
      1626055868,
      1626055868,
      1626055868,
      1626055868,
      1626055868,
      1626055868,
      1626055868,
      1626055868,
      1626055868,
      1626055868,
      1626055868,
      1626055868,
      1626055868,
      1626055867,
      1626055867,
      1626055867,
      1626055867,
      1626055867,
      1626055867,
      1626055867,
      1626055867,
      1626055867,
      1626055867,
      1626055867,
      1626055867,
      1626055867,
      1626055867,
      1626055867,
      1626055867,
      1626055867,
      1626055867,
      1626055867,
      1626055867,
      1626055867,
      1626055867,
      1626055867,
      1626055867,
      1626055867,
      1626055867,
      1626055867,
      1626055867,
      1626055867,
      1626055867,
      1626055867,
      1626055867,
      1626055867,
      1626055867,
      1626055867,
      1626055867,
      1626055867,
      1626055867,
      1626055867,
      1626055867,
      1626055867,
      1626055867,
      1626055867,
      1626055867,
      1626055867,
      1626055867,
      1626055867,
      1626055867,
      1626055867,
      1626055867,
      1626055867,
      1626055867,
      1626055867,
      1626055867,
      1626055867,
      1626055867,
      1626055867,
      1626055867,
      1626055867,
      1626055867,
      1626055867,
      1626055867,
      1626055867,
      1626055867,
      1626055867,
      1626055867,
      1626055867,
      1626055867,
      1626055867,
      1626055867,
      1626055867,
      1626055867,
      1626055867,
      1626055867,
      1626055867,
      1626055867,
      1626055867,
      1626055867,
      1626055867,
      1626055867,
      1626055867,
      1626055867,
      1626055867,
      1626055867,
      1626055867,
      1626055867,
      1626055867,
      1626055867,
      1626055867,
      1626055867,
      1626055867,
      1626055867,
      1626055867,
      1626055867,
      1626055867,
      1626055867,
      1626055867,
      1626055867,
      1626055867,
      1626055867,
      1626055867,
      1626055867,
      1626055867,
      1626055867,
      1626055867,
      1626055867,
      1626055867,
      1626055867,
      1626055867,
      1626055867,
      1626055867,
      1626055867,
      1626055867,
      1626055867,
      1626055867,
      1626055867,
      1626055867,
      1626055867,
      1626055867,
      1626055867,
      1626055867,
      1626055867,
      1626055867,
      1626055867,
      1626055867,
      1626055867,
      1626055866,
      1626055866,
      1626055866,
      1626055866,
      1626055866,
      1626055866,
      1626055866,
      1626055866,
      1626055866,
      1626055866,
      1626055866,
      1626055866,
      1626055866,
      1626055866,
      1626055866,
      1626055866,
      1626055866,
      1626055866,
      1626055866,
      1626055866,
      1626055866,
      1626055866,
      1626055866,
      1626055866,
      1626055866,
      1626055866,
      1626055866,
      1626055866,
      1626055866,
      1626055866,
      1626055866,
      1626055866,
      1626055866,
      1626055866,
      1626055866,
      1626055866,
      1626055866,
      1626055866,
      1626055866,
      1626055866,
      1626055866,
      1626055866,
      1626055866,
      1626055866,
      1626055866,
      1626055866,
      1626055866,
      1626055866,
      1626055866,
      1626055866,
      1626055866,
      1626055866,
      1626055866,
      1626055866,
      1626055866,
      1626055866,
      1626055866,
      1626055866,
      1626055866,
      1626055866,
      1626055866,
      1626055866,
      1626055866,
      1626055866,
      1626055866,
      1626055866,
      1626055866,
      1626055866,
      1626055866,
      1626055866,
      1626055866,
      1626055866,
      1626055866,
      1626055866,
      1626055866,
      1626055866,
      1626055866,
      1626055866,
      1626055866,
      1626055866,
      1626055866,
      1626055866,
      1626055866,
      1626055866,
      1626055866,
      1626055866,
      1626055866,
      1626055866,
      1626055866,
      1626055866,
      1626055866,
      1626055866,
      1626055866,
      1626055866,
      1626055866,
      1626055866,
      1626055866,
      1626055866,
      1626055866,
      1626055866,
      1626055866,
      1626055866,
      1626055866,
      1626055866,
      1626055866,
      1626055866,
      1626055866,
      1626055866,
      1626055866,
      1626055866,
      1626055866,
      1626055866,
      1626055866,
      1626055866,
      1626055866,
      1626055866,
      1626055866,
      1626055866,
      1626055866,
      1626055866,
      1626055866,
      1626055866,
      1626055866,
      1626055866,
      1626055866,
      1626055866,
      1626055866,
      1626055866,
      1626055866,
      1626055866,
      1626055866,
      1626055865,
      1626055865,
      1626055865,
      1626055865,
      1626055865,
      1626055865,
      1626055865,
      1626055865,
      1626055865,
      1626055865,
      1626055865,
      1626055865,
      1626055865,
      1626055865,
      1626055865,
      1626055865,
      1626055865,
      1626055865,
      1626055865,
      1626055865,
      1626055865,
      1626055865,
      1626055865,
      1626055865,
      1626055865,
      1626055865,
      1626055865,
      1626055865,
      1626055865,
      1626055865,
      1626055865,
      1626055865,
      1626055865,
      1626055865,
      1626055865,
      1626055865,
      1626055865,
      1626055865,
      1626055865,
      1626055865,
      1626055865,
      1626055865,
      1626055865,
      1626055865,
      1626055865,
      1626055865,
      1626055865,
      1626055865,
      1626055865,
      1626055865,
      1626055865,
      1626055865,
      1626055865,
      1626055865,
      1626055865,
      1626055865,
      1626055865,
      1626055865,
      1626055865,
      1626055865,
      1626055865,
      1626055865,
      1626055865,
      1626055865,
      1626055865,
      1626055865,
      1626055865,
      1626055865,
      1626055865,
      1626055865,
      1626055865,
      1626055865,
      1626055865,
      1626055865,
      1626055865,
      1626055865,
      1626055865,
      1626055865,
      1626055865,
      1626055865,
      1626055865,
      1626055865,
      1626055865,
      1626055865,
      1626055865,
      1626055865,
      1626055865,
      1626055865,
      1626055865,
      1626055865,
      1626055865,
      1626055865,
      1626055865,
      1626055865,
      1626055865,
      1626055865,
      1626055865,
      1626055865,
      1626055865,
      1626055865,
      1626055865,
      1626055865,
      1626055865,
      1626055865,
      1626055865,
      1626055865,
      1626055865,
      1626055865,
      1626055865,
      1626055865,
      1626055865,
      1626055865,
      1626055865,
      1626055865,
      1626055865,
      1626055865,
      1626055865,
      1626055865,
      1626055865,
      1626055865,
      1626055865,
      1626055865,
      1626055865,
      1626055865,
      1626055865,
      1626055865,
      1626055865,
      1626055865,
      1626055865,
      1626055865,
      1626055865,
      1626055865,
      1626055865,
      1626055865,
      1626055865,
      1626055865,
      1626055865,
      1626055865,
      1626055865,
      1626055865,
      1626055865,
      1626055865,
      1626055865,
      1626055865,
      1626055865,
      1626055865,
      1626055865,
      1626055865,
      1626055865,
      1626055865,
      1626055865,
      1626055864,
      1626055864,
      1626055864,
      1626055864,
      1626055864,
      1626055864,
      1626055864,
      1626055864,
      1626055864,
      1626055864,
      1626055864,
      1626055864,
      1626055864,
      1626055864,
      1626055864,
      1626055864,
      1626055864,
      1626055864,
      1626055864,
      1626055864,
      1626055864,
      1626055864,
      1626055864,
      1626055864,
      1626055864,
      1626055864,
      1626055864,
      1626055864,
      1626055864,
      1626055864,
      1626055864,
      1626055864,
      1626055864,
      1626055864,
      1626055864,
      1626055864,
      1626055864,
      1626055864,
      1626055864,
      1626055864,
      1626055864,
      1626055864,
      1626055864,
      1626055864,
      1626055864,
      1626055864,
      1626055864,
      1626055864,
      1626055864,
      1626055864,
      1626055864,
      1626055864,
      1626055864,
      1626055864,
      1626055864,
      1626055864,
      1626055864,
      1626055864,
      1626055864,
      1626055864,
      1626055864,
      1626055864,
      1626055864,
      1626055864,
      1626055864,
      1626055864,
      1626055864,
      1626055864,
      1626055864,
      1626055864,
      1626055864,
      1626055864,
      1626055864,
      1626055864,
      1626055864,
      1626055864,
      1626055864,
      1626055864,
      1626055864,
      1626055864,
      1626055864,
      1626055864,
      1626055864,
      1626055864,
      1626055864,
      1626055864,
      1626055864,
      1626055864,
      1626055864,
      1626055864,
      1626055864,
      1626055864,
      1626055864,
      1626055864,
      1626055864,
      1626055864,
      1626055864,
      1626055864,
      1626055864,
      1626055864,
      1626055864,
      1626055864,
      1626055864,
      1626055864,
      1626055864,
      1626055864,
      1626055864,
      1626055864,
      1626055864,
      1626055864,
      1626055864,
      1626055864,
      1626055864,
      1626055864,
      1626055864,
      1626055864,
      1626055864,
      1626055864,
      1626055864,
      1626055864,
      1626055864,
      1626055864,
      1626055864,
      1626055864,
      1626055864,
      1626055864,
      1626055864,
      1626055864,
      1626055864,
      1626055864,
      1626055863,
      1626055863,
      1626055863,
      1626055863,
      1626055863,
      1626055845,
      1626055845,
      1626055845,
      1626055845,
      1626055845,
      1626055845,
      1626055845,
      1626055845,
      1626055845,
      1626055845,
      1626055845,
      1626055845,
      1626055845,
      1626055845,
      1626055845,
      1626055845,
      1626055845,
      1626055845,
      1626055845,
      1626055845,
      1626055845,
      1626055845,
      1626055845,
      1626055845,
      1626055845,
      1626055845,
      1626055840,
      1626055840,
      1626055840,
      1626055840,
      1626055840,
      1626055839,
      1626055839,
      1626055839,
      1626055839,
      1626055838,
      1626055838,
      1626055838,
      1626055838,
      1626055838,
      1626055837,
      1626055837,
      1626055837,
      1626055837,
      1626055746,
      1626055746,
      1626055746,
      1626055746,
      1626055745,
      1626055745,
      1626055745,
      1626055745,
      1626055745,
      1626055745,
      1626055745,
      1626055745,
      1626055744,
      1626055744,
      1626055744,
      1626055744,
      1626055744,
      1626055744,
      1626055744,
      1626055744,
      1626055744,
      1626055744,
      1626055744,
      1626055744,
      1626055744,
      1626055744,
      1626055744,
      1626055744,
      1626055744,
      1626055744,
      1626055744,
      1626055744,
      1626055744,
      1626055744,
      1626055744,
      1626055744,
      1626055743,
      1626055743,
      1626055743,
      1626055743,
      1626055743,
      1626055743,
      1626055743,
      1626055743,
      1626055743,
      1626055743,
      1626055743,
      1626055743,
      1626055743,
      1626055743,
      1626055743,
      1626055743,
      1626055743,
      1626055743,
      1626055743,
      1626055743,
      1626055743,
      1626055743,
      1626055743,
      1626055743,
      1626055743,
      1626055743,
      1626055743,
      1626055743,
      1626055743,
      1626055743,
      1626055743,
      1626055743,
      1626055743,
      1626055743,
      1626055743,
      1626055743,
      1626055743,
      1626055743,
      1626055743,
      1626055743,
      1626055743,
      1626055743,
      1626055743,
      1626055743,
      1626055743,
      1626055743,
      1626055743,
      1626055743,
      1626055743,
      1626055743,
      1626055743,
      1626055743,
      1626055743,
      1626055743,
      1626055743,
      1626055743,
      1626055743,
      1626055743,
      1626055743,
      1626055743,
      1626055743,
      1626055743,
      1626055743,
      1626055743,
      1626055743,
      1626055743,
      1626055743,
      1626055743,
      1626055743,
      1626055743,
      1626055743,
      1626055743,
      1626055743,
      1626055743,
      1626055743,
      1626055743,
      1626055743,
      1626055743,
      1626055743,
      1626055743,
      1626055743,
      1626055743,
      1626055743,
      1626055743,
      1626055743,
      1626055743,
      1626055743,
      1626055743,
      1626055743,
      1626055743,
      1626055743,
      1626055743,
      1626055743,
      1626055743,
      1626055743,
      1626055743,
      1626055743,
      1626055743,
      1626055743,
      1626055743,
      1626055743,
      1626055743,
      1626055743,
      1626055743,
      1626055743,
      1626055743,
      1626055743,
      1626055743,
      1626055743,
      1626055743,
      1626055743,
      1626055743,
      1626055743,
      1626055743,
      1626055743,
      1626055743,
      1626055743,
      1626055743,
      1626055743,
      1626055743,
      1626055743,
      1626055743,
      1626055743,
      1626055743,
      1626055743,
      1626055743,
      1626055743,
      1626055743,
      1626055743,
      1626055743,
      1626055743,
      1626055743,
      1626055743,
      1626055743,
      1626055743,
      1626055743,
      1626055743,
      1626055743,
      1626055743,
      1626055743,
      1626055743,
      1626055743,
      1626055743,
      1626055743,
      1626055743,
      1626055743,
      1626055743,
      1626055743,
      1626055743,
      1626055743,
      1626055743,
      1626055743,
      1626055743,
      1626055743,
      1626055743,
      1626055743,
      1626055743,
      1626055743,
      1626055743,
      1626055743,
      1626055743,
      1626055743,
      1626055743,
      1626055743,
      1626055743,
      1626055743,
      1626055743,
      1626055743,
      1626055743,
      1626055743,
      1626055743,
      1626055743,
      1626055743,
      1626055743,
      1626055743,
      1626055743,
      1626055743,
      1626055743,
      1626055743,
      1626055743,
      1626055743,
      1626055743,
      1626055743,
      1626055743,
      1626055743,
      1626055743,
      1626055743,
      1626055743,
      1626055743,
      1626055743,
      1626055743,
      1626055743,
      1626055743,
      1626055743,
      1626055743,
      1626055743,
      1626055743,
      1626055743,
      1626055743,
      1626055743,
      1626055743,
      1626055743,
      1626055743,
      1626055743,
      1626055743,
      1626055743,
      1626055743,
      1626055743,
      1626055743,
      1626055743,
      1626055743,
      1626055743,
      1626055743,
      1626055743,
      1626055743,
      1626055743,
      1626055743,
      1626055743,
      1626055743,
      1626055743,
      1626055743,
      1626055743,
      1626055743,
      1626055743,
      1626055743,
      1626055743,
      1626055743,
      1626055743,
      1626055743,
      1626055743,
      1626055743,
      1626055743,
      1626055743,
      1626055743,
      1626055743,
      1626055743,
      1626055743,
      1626055743,
      1626055743,
      1626055743,
      1626055743,
      1626055743,
      1626055743,
      1626055743,
      1626055743,
      1626055743,
      1626055743,
      1626055743,
      1626055743,
      1626055743,
      1626055743,
      1626055743,
      1626055743,
      1626055743,
      1626055743,
      1626055743,
      1626055743,
      1626055743,
      1626055743,
      1626055743,
      1626055743,
      1626055743,
      1626055743,
      1626055743,
      1626055743,
      1626055743,
      1626055743,
      1626055743,
      1626055743,
      1626055743,
      1626055743,
      1626055743,
      1626055743,
      1626055743,
      1626055743,
      1626055743,
      1626055743,
      1626055743,
      1626055743,
      1626055743,
      1626055743,
      1626055743,
      1626055743,
      1626055743,
      1626055743,
      1626055743,
      1626055743,
      1626055743,
      1626055743,
      1626055743,
      1626055743,
      1626055743,
      1626055743,
      1626055743,
      1626055743,
      1626055743,
      1626055743,
      1626055743,
      1626055743,
      1626055743,
      1626055743,
      1626055743,
      1626055743,
      1626055743,
      1626055743,
      1626055743,
      1626055743,
      1626055743,
      1626055743,
      1626055743,
      1626055743,
      1626055743,
      1626055743,
      1626055743,
      1626055743,
      1626055743,
      1626055743,
      1626055743,
      1626055743,
      1626055743,
      1626055743,
      1626055743,
      1626055743,
      1626055743,
      1626055743,
      1626055743,
      1626055743,
      1626055743,
      1626055743,
      1626055743,
      1626055743,
      1626055743,
      1626055743,
      1626055743,
      1626055743,
      1626055743,
      1626055743,
      1626055743,
      1626055743,
      1626055743,
      1626055743,
      1626055743,
      1626055743,
      1626055743,
      1626055743,
      1626055743,
      1626055743,
      1626055743,
      1626055743,
      1626055743,
      1626055743,
      1626055743,
      1626055743,
      1626055743,
      1626055743,
      1626055743,
      1626055743,
      1626055743,
      1626055743,
      1626055743,
      1626055743,
      1626055743,
      1626055743,
      1626055743,
      1626055743,
      1626055743,
      1626055743,
      1626055743,
      1626055743,
      1626055743,
      1626055743,
      1626055743,
      1626055743,
      1626055743,
      1626055743,
      1626055743,
      1626055743,
      1626055743,
      1626055743,
      1626055743,
      1626055743,
      1626055743,
      1626055743,
      1626055743,
      1626055743,
      1626055743,
      1626055743,
      1626055743,
      1626055743,
      1626055743,
      1626055743,
      1626055743,
      1626055743,
      1626055743,
      1626055743,
      1626055743,
      1626055743,
      1626055743,
      1626055743,
      1626055743,
      1626055743,
      1626055743,
      1626055743,
      1626055743,
      1626055743,
      1626055743,
      1626055743,
      1626055743,
      1626055743,
      1626055743,
      1626055743,
      1626055743,
      1626055743,
      1626055743,
      1626055743,
      1626055743,
      1626055743,
      1626055743,
      1626055743,
      1626055743,
      1626055743,
      1626055743,
      1626055743,
      1626055743,
      1626055743,
      1626055743,
      1626055743,
      1626055743,
      1626055743,
      1626055743,
      1626055743,
      1626055743,
      1626055743,
      1626055743,
      1626055743,
      1626055743,
      1626055743,
      1626055743,
      1626055743,
      1626055743,
      1626055743,
      1626055743,
      1626055743,
      1626055743,
      1626055743,
      1626055743,
      1626055743,
      1626055743,
      1626055743,
      1626055740,
      1626055740,
      1626055740,
      1626055740,
      1626055740,
      1626055740,
      1626055740,
      1626055740,
      1626055740,
      1626055740,
      1626055740,
      1626055740,
      1626055740,
      1626055740,
      1626055740,
      1626055740,
      1626055740,
      1626055740,
      1626055740,
      1626055740,
      1626055740,
      1626055740,
      1626055740,
      1626055740,
      1626055740,
      1626055740,
      1626055740,
      1626055740,
      1626055740,
      1626055740,
      1626055740,
      1626055740,
      1626055740,
      1626055735,
      1626055735,
      1626055733,
      1626055733,
      1626055733,
      1626055733,
      1626055733,
      1626055733,
      1626055733,
      1626055733,
      1626055733,
      1626055733,
      1626055733,
      1626055733,
      1626055730,
      1626055729,
      1626055729,
      1626055729,
      1626055729,
      1626055729,
      1626055729,
      1626055729,
      1626055693,
      1626055693,
      1626055693,
      1626055693,
      1626055693,
      1626055693,
      1626055693,
      1626055693,
      1626055693,
      1626055693,
      1626055693,
      1626055693,
      1626055693,
      1626055693,
      1626055693,
      1626055693,
      1626055693,
      1626055693,
      1626055693,
      1626055693,
      1626055693,
      1626055693,
      1626055692,
      1626055692,
      1626055692,
      1626055692,
      1626055692,
      1626055692,
      1626055692,
      1626055692,
      1626055692,
      1626055692,
      1626055692,
      1626055692,
      1626055692,
      1626055692,
      1626055692,
      1626055692,
      1626055692,
      1626055679,
      1626055679,
      1626055679,
      1626055679,
      1626055679,
      1626055679,
      1626055679,
      1626055679,
      1626055679,
      1626055679,
      1626055679,
      1626055679,
      1626055679,
      1626055679,
      1626055679,
      1626055679,
      1626055679,
      1626055679,
      1626055679,
      1626055679,
      1626055679,
      1626055679,
      1626055679,
      1626055679,
      1626055679,
      1626055679,
      1626055679,
      1626055679,
      1626055679,
      1626055679,
      1626055679,
      1626055679,
      1626055679,
      1626055679,
      1626055679,
      1626055679,
      1626055679,
      1626055679,
      1626055679,
      1626055679,
      1626055679,
      1626055679,
      1626055679,
      1626055679,
      1626055679,
      1626055679,
      1626055679,
      1626055679,
      1626055679,
      1626055679,
      1626055679,
      1626055679,
      1626055679,
      1626055679,
      1626055679,
      1626055679,
      1626055679,
      1626055679,
      1626055679,
      1626055679,
      1626055678,
      1626055678,
      1626055678,
      1626055678,
      1626055678,
      1626055678,
      1626055678,
      1626055678,
      1626055678,
      1626055678,
      1626055678,
      1626055678,
      1626055674,
      1626055674,
      1626055674,
      1626055674,
      1626055674,
      1626055672,
      1626055672,
      1626055672,
      1626055672,
      1626055672,
      1626055672,
      1626055672,
      1626055672,
      1626055672,
      1626055672,
      1626055672,
      1626055672,
      1626055672,
      1626055672,
      1626055672,
      1626055672,
      1626055671,
      1626055671,
      1626055671,
      1626055671,
      1626055671,
      1626055671,
      1626055671,
      1626055671,
      1626055671,
      1626055671,
      1626055671,
      1626055671,
      1626055671,
      1626055671,
      1626055671,
      1626055671,
      1626055671,
      1626055671,
      1626055671,
      1626055671,
      1626055671,
      1626055671,
      1626055671,
      1626055671,
      1626055671,
      1626055671,
      1626055652,
      1626055652,
      1626055652,
      1626055652,
      1626055652,
      1626055652,
      1626055596,
      1626055596,
      1626055596,
      1626055596,
      1626055596,
      1626055596,
      1626055596,
      1626055596,
      1626055596,
      1626055596,
      1626055596,
      1626055596,
      1626055596,
      1626055596,
      1626055596,
      1626055596,
      1626055596,
      1626055596,
      1626055596,
      1626055596,
      1626055596,
      1626055596,
      1626055596,
      1626055596,
      1626055596,
      1626055595,
      1626055595,
      1626055595,
      1626055595,
      1626055595,
      1626055595,
      1626055595,
      1626055595,
      1626055595,
      1626055595,
      1626055595,
      1626055595,
      1626055595,
      1626055595,
      1626055595,
      1626055595,
      1626055595,
      1626055595,
      1626055595,
      1626055595,
      1626055595,
      1626055595,
      1626055595,
      1626055595,
      1626055595,
      1626055595,
      1626055595,
      1626055595,
      1626055595,
      1626055595,
      1626055595,
      1626055595,
      1626055595,
      1626055595,
      1626055595,
      1626055595,
      1626055595,
      1626055595,
      1626055595,
      1626055595,
      1626055595,
      1626055595,
      1626055595,
      1626055595,
      1626055595,
      1626055595,
      1626055595,
      1626055595,
      1626055595,
      1626055595,
      1626055595,
      1626055595,
      1626055595,
      1626055595,
      1626055595,
      1626055595,
      1626055595,
      1626055595,
      1626055595,
      1626055595,
      1626055595,
      1626055595,
      1626055595,
      1626055594,
      1626055594,
      1626055594,
      1626055594,
      1626055594,
      1626055594,
      1626055594,
      1626055594,
      1626055594,
      1626055594,
      1626055594,
      1626055594,
      1626055594,
      1626055594,
      1626055594,
      1626055594,
      1626055594,
      1626055594,
      1626055594,
      1626055594,
      1626055594,
      1626055594,
      1626055594,
      1626055594,
      1626055594,
      1626055594,
      1626055594,
      1626055594,
      1626055594,
      1626055594,
      1626055594,
      1626055594,
      1626055594,
      1626055594,
      1626055594,
      1626055594,
      1626055594,
      1626055594,
      1626055594,
      1626055594,
      1626055594,
      1626055594,
      1626055594,
      1626055594,
      1626055594,
      1626055594,
      1626055594,
      1626055594,
      1626055594,
      1626055594,
      1626055594,
      1626055594,
      1626055594,
      1626055594,
      1626055594,
      1626055594,
      1626055594,
      1626055594,
      1626055594,
      1626055594,
      1626055594,
      1626055594,
      1626055594,
      1626055594,
      1626055594,
      1626055594,
      1626055594,
      1626055594,
      1626055594,
      1626055594,
      1626055594,
      1626055594,
      1626055594,
      1626055594,
      1626055594,
      1626055593,
      1626055593,
      1626055593,
      1626055593,
      1626055593,
      1626055593,
      1626055593,
      1626055593,
      1626055593,
      1626055592,
      1626055592,
      1626055592,
      1626055592,
      1626055592,
      1626055592,
      1626055592,
      1626055592,
      1626055592,
      1626055592,
      1626055592,
      1626055592,
      1626055591,
      1626055591,
      1626055591,
      1626055591,
      1626055591,
      1626055591,
      1626055591,
      1626055591,
      1626055591,
      1626055591,
      1626055591,
      1626055590,
      1626055590,
      1626055590,
      1626055590,
      1626055590,
      1626055590,
      1626055590,
      1626055590,
      1626055590,
      1626055590,
      1626055590,
      1626055590,
      1626055590,
      1626055590,
      1626055590,
      1626055590,
      1626055590,
      1626055590,
      1626055590,
      1626055590,
      1626055590,
      1626055590,
      1626055590,
      1626055590,
      1626055590,
      1626055590,
      1626055590,
      1626055590,
      1626055590,
      1626055590,
      1626055590,
      1626055590,
      1626055590,
      1626055589,
      1626055589,
      1626055589,
      1626055589,
      1626055589,
      1626055589,
      1626055589,
      1626055589,
      1626055589,
      1626055589,
      1626055588,
      1626055588,
      1626055345,
      1626055290,
      1626055290,
      1626055290,
      1626055290,
      1626055257,
      1626055257,
      1626055257,
      1626055257,
      1626055256,
      1626055256,
      1626055256,
      1626055256,
      1626055256,
      1626055256,
      1626055256,
      1626055256,
      1626055256,
      1626055256,
      1626055256,
      1626055255,
      1626055255,
      1626055255,
      1626055255,
      1626055255,
      1626055253,
      1626055253,
      1626055253,
      1626055253,
      1626055253,
      1626055253,
      1626055253,
      1626055253,
      1626055253,
      1626055252,
      1626055252,
      1626055252,
      1626055252,
      1626055252,
      1626055252,
      1626055251,
      1626055251,
      1626055251,
      1626055251,
      1626055251,
      1626055250,
      1626055250,
      1626055250,
      1626055250,
      1626055250,
      1626055250,
      1626055249,
      1626055249,
      1626055249,
      1626055249,
      1626055249,
      1626055249,
      1626055249,
      1626055249,
      1626055249,
      1626055249,
      1626055249,
      1626055248,
      1626055248,
      1626055248,
      1626055247,
      1626055247,
      1626055247,
      1626055247,
      1626055247,
      1626055246,
      1626055246,
      1626055246,
      1626055246,
      1626055246,
      1626055246,
      1626055219,
      1626055219,
      1626055219,
      1626055219,
      1626052207,
      1626052207,
      1626051965,
      1626051965,
      1626051626,
      1626051613,
      1626051613,
      1626051613,
      1626051613,
      1626051613,
      1626051613,
      1626051613,
      1626051612,
      1626051612,
      1626051612,
      1626051612,
      1626051612,
      1626051611,
      1626051611,
      1626051611,
      1626051611,
      1626051611,
      1626051610,
      1626051610,
      1626051610,
      1626051610,
      1626051610,
      1626051610,
      1626051610,
      1626051610,
      1626051610,
      1626051610,
      1626051610,
      1626051610,
      1626051610,
      1626051610,
      1626051610,
      1626051610,
      1626051610,
      1626051610,
      1626051610,
      1626051610,
      1626051610,
      1626051610,
      1626051610,
      1626051610,
      1626051610,
      1626051610,
      1626051610,
      1626051610,
      1626051609,
      1626051609,
      1626051609,
      1626051609,
      1626051609,
      1626051609,
      1626051609,
      1626051609,
      1626051609,
      1626051609,
      1626051609,
      1626051609,
      1626051609,
      1626051609,
      1626051609,
      1626051609,
      1626051608,
      1626051608,
      1626051608,
      1626051608,
      1626051608,
      1626051608,
      1626051607,
      1626051607,
      1626051607,
      1626051607,
      1626051607,
      1626051607,
      1626051607,
      1626051607,
      1626051607,
      1626051607,
      1626051607,
      1626051607,
      1626051607,
      1626051607,
      1626051607,
      1626051607,
      1626051607,
      1626051607,
      1626051607,
      1626051607,
      1626051607,
      1626051606,
      1626051606,
      1626051606,
      1626051606,
      1626051606,
      1626051606,
      1626051606,
      1626051606,
      1626051606,
      1626051606,
      1626051606,
      1626051606,
      1626051606,
      1626051606,
      1626051606,
      1626051606,
      1626051606,
      1626051606,
      1626051606,
      1626051605,
      1626051605,
      1626051605,
      1626051605,
      1626051605,
      1626051605,
      1626051605,
      1626051605,
      1626051605,
      1626051605,
      1626051605,
      1626051605,
      1626051605,
      1626051605,
      1626051605,
      1626051605,
      1626051604,
      1626051604,
      1626051604,
      1626051604,
      1626051604,
      1626051604,
      1626051604,
      1626051604,
      1626051604,
      1626051604,
      1626051604,
      1626051604,
      1626051604,
      1626051604,
      1626051604,
      1626051604,
      1626051604,
      1626051604,
      1626051604,
      1626051604,
      1626051604,
      1626051604,
      1626051604,
      1626051603,
      1626051603,
      1626051603,
      1626051603,
      1626051603,
      1626051603,
      1626051603,
      1626051603,
      1626051603,
      1626051603,
      1626051603,
      1626051603,
      1626051603,
      1626051603,
      1626051603,
      1626051603,
      1626051602,
      1626048662,
      1626048662,
      1626048662,
      1626048662,
      1626048662,
      1626048662,
      1626048662,
      1626048662,
      1626048644,
      1626048644,
      1626048644,
      1626048644,
      1626048602,
      1626048602,
      1626048366,
      1626048366,
      1626048366,
      1626048366,
      1626048362,
      1626048362,
      1626048311,
      1626048311,
      1626048311,
      1626048311,
      1626048310,
      1626048310,
      1626048310,
      1626048310,
      1626048307,
      1626048307,
      1626048307,
      1626048307,
      1626048307,
      1626048307,
      1626048307,
      1626048307,
      1626048159,
      1626048159,
      1626048159,
      1626048159,
      1626048107,
      1626048107,
      1626048107,
      1626048046,
      1626048046,
      1626048046,
      1626048046,
      1626048040,
      1626048040,
      1626048040,
      1626048040,
      1626048020,
      1626048020,
      1626048020,
      1626048020,
      1626048020,
      1626048020,
      1626048020,
      1626048020,
      1626048020,
      1626048020,
      1626048020,
      1626048020,
      1626048020,
      1626048020,
      1626048020,
      1626048020,
      1626048008,
      1626048008,
      1626048006,
      1626048006,
      1626048003,
      1626048003,
      1626048003,
      1626048003,
      1626048001,
      1626048001,
      1626048001,
      1626048001,
      1626048000,
      1626048000,
      1626048000,
      1626048000,
      1626048000,
      1626048000,
      1626048000,
      1626048000,
      1626048000,
      1626048000,
      1626048000,
      1626048000,
      1626048000,
      1626048000,
      1626048000,
      1626048000,
      1626048000,
      1626048000,
      1626048000,
      1626048000,
      1626048000,
      1626048000,
      1626048000,
      1626048000,
      1626048000,
      1626048000,
      1626048000,
      1626048000,
      1626048000,
      1626048000,
      1626048000,
      1626048000,
      1626048000,
      1626048000,
      1626048000,
      1626048000,
      1626048000,
      1626048000,
      1626048000,
      1626048000,
      1626048000,
      1626048000,
      1626048000,
      1626048000,
      1626048000,
      1626048000,
      1626048000,
      1626048000,
      1626048000,
      1626048000,
      1626048000,
      1626048000,
      1626048000,
      1626048000,
      1626048000,
      1626048000,
      1626048000,
      1626048000,
      1626048000,
      1626048000,
      1626048000,
      1626048000,
      1626048000,
      1626048000,
      1626048000,
      1626048000,
      1626048000,
      1626048000,
      1626048000,
      1626048000,
      1626048000,
      1626048000,
      1626048000,
      1626048000,
      1626048000,
      1626048000,
      1626048000,
      1626048000,
      1626048000,
      1626048000,
      1626048000,
      1626048000,
      1626048000,
      1626048000,
      1626048000,
      1626048000,
      1626048000,
      1626048000,
      1626047767,
      1626047767,
      1626047767,
      1626047767,
      1626046322,
      1626046322,
      1626046237,
      1626046237,
      1626045686,
      1626045686,
      1626045686,
      1626045686,
      1626044467,
      1626044467,
      1626044466,
      1626044465,
      1626044456,
      1626044456,
      1626044456,
      1626044456,
      1626044443,
      1626044443,
      1626044443,
      1626044443,
      1626044409,
      1626044409,
      1626044409,
      1626044409,
      1626044406,
      1626044406,
      1626044406,
      1626044406,
      1626044405,
      1626044405,
      1626044405,
      1626044405,
      1626044404,
      1626044404,
      1626044404,
      1626044404,
      1626044404,
      1626044404,
      1626044404,
      1626044404,
      1626044404,
      1626044404,
      1626044404,
      1626044404,
      1626044404,
      1626044404,
      1626044404,
      1626044404,
      1626044404,
      1626041857,
      1626041857,
      1626041856,
      1626041856,
      1626041856,
      1626041856,
      1626041854,
      1626041854,
      1626041403,
      1626041403,
      1626041403,
      1626041403,
      1626041202,
      1626041202,
      1626041202,
      1626041202,
      1626041194,
      1626041194,
      1626041194,
      1626041194,
      1626041108,
      1626041108,
      1626041095,
      1626041095,
      1626041048,
      1626041048,
      1626041048,
      1626041048,
      1626041013,
      1626041013,
      1626041001,
      1626041001,
      1626041001,
      1626041001,
      1626040977,
      1626040977,
      1626040977,
      1626040977,
      1626040972,
      1626040972,
      1626040966,
      1626040966,
      1626040952,
      1626040952,
      1626040952,
      1626040952,
      1626040944,
      1626040944,
      1626040944,
      1626040944,
      1626040939,
      1626040939,
      1626040939,
      1626040939,
      1626040932,
      1626040932,
      1626040931,
      1626040931,
      1626040931,
      1626040931,
      1626040931,
      1626040928,
      1626040928,
      1626040923,
      1626040923,
      1626040922,
      1626040922,
      1626040922,
      1626040919,
      1626040919,
      1626040919,
      1626040919,
      1626040915,
      1626040915,
      1626040914,
      1626040914,
      1626040909,
      1626040909,
      1626040909,
      1626040909,
      1626040903,
      1626040903,
      1626040903,
      1626040903,
      1626040895,
      1626040895,
      1626040895,
      1626040895,
      1626040875,
      1626040875,
      1626040875,
      1626040875,
      1626040875,
      1626040868,
      1626040868,
      1626040868,
      1626040868,
      1626040861,
      1626040861,
      1626040861,
      1626040861,
      1626040859,
      1626040859,
      1626040859,
      1626040859,
      1626040859,
      1626040845,
      1626040845,
      1626040845,
      1626040845,
      1626040835,
      1626040835,
      1626040835,
      1626040835,
      1626040831,
      1626040831,
      1626040831,
      1626040825,
      1626040825,
      1626040825,
      1626040825,
      1626040825,
      1626040823,
      1626040823,
      1626040823,
      1626040823,
      1626040821,
      1626040821,
      1626040821,
      1626040821,
      1626040820,
      1626040820,
      1626040820,
      1626040820,
      1626040820,
      1626040820,
      1626040820,
      1626040820,
      1626040815,
      1626040815,
      1626040815,
      1626040815,
      1626040814,
      1626040814,
      1626040814,
      1626040814,
      1626040804,
      1626040804,
      1626040804,
      1626040804,
      1626039399,
      1626039399,
      1626039399,
      1626038416,
      1626038416,
      1626038416,
      1626038416,
      1626038414,
      1626038414,
      1626038402,
      1626038402,
      1626037208,
      1626037208,
      1626037208,
      1626037208,
      1626033607,
      1626033607,
      1626033607,
      1626033607,
      1626030910,
      1626030910,
      1626030581,
      1626030580,
      1626030578,
      1626030577,
      1626030575,
      1626030572,
      1626030570,
      1626030545,
      1626030544,
      1626030543,
      1626030541,
      1626030541,
      1626030540,
      1626030539,
      1626030538,
      1626030536,
      1626030534,
      1626030532,
      1626030531,
      1626030529,
      1626030527,
      1626030521,
      1626030520,
      1626030519,
      1626030517,
      1626030517,
      1626030515,
      1626030514,
      1626030510,
      1626030508,
      1626030474,
      1626030401,
      1626030378,
      1626030330,
      1626030329,
      1626030328,
      1626030327,
      1626030326,
      1626030323,
      1626030318,
      1626030317,
      1626030315,
      1626030314,
      1626030313,
      1626030312,
      1626030310,
      1626030309,
      1626030307,
      1626030306,
      1626030305,
      1626028203,
      1626028203,
      1626026413,
      1626026413,
      1626026408,
      1626026408,
      1626026408,
      1626026408,
      1626026407,
      1626026407,
      1626024049,
      1626024047,
      1626023074,
      1626023074,
      1626023074,
      1626023043,
      1626023043,
      1626023043,
      1626023043,
      1626022882,
      1626022882,
      1626021045,
      1626021045,
      1626021045,
      1626021045,
      1626020391,
      1626019203,
      1626019203,
      1626014406,
      1626014406,
      1626014406,
      1626014406,
      1626014406,
      1626014406,
      1626014406,
      1626014406,
      1626014229,
      1626014229,
      1626013802,
      1626013802,
      1626009945,
      1626009945,
      1626009945,
      1626009945,
      1626009657,
      1626009657,
      1626008828,
      1626008828,
      1626008621,
      1626008621,
      1626008532,
      1626008532,
      1626008451,
      1626008451,
      1626007266,
      1626007266,
      1626004208,
      1626004208,
      1626004208,
      1626001837,
      1626001837,
      1626001837,
      1626001837,
      1626001482,
      1626001482,
      1626001482,
      1626001482,
      1626001246,
      1626001246,
      1626001246,
      1626001246,
      1626001244,
      1626001244,
      1626001244,
      1626001244,
      1626001208,
      1626001208,
      1626001208,
      1626001208,
      1626001203,
      1626001203,
      1626001203,
      1626001203,
      1625999408,
      1625999408,
      1625999408,
      1625999408,
      1625997910,
      1625997910,
      1625997730,
      1625997730,
      1625997603,
      1625997603,
      1625997603,
      1625997603,
      1625993168,
      1625993168,
      1625993168,
      1625993168,
      1625991921,
      1625991921,
      1625991921,
      1625991921,
      1625990491,
      1625990491,
      1625990491,
      1625990491,
      1625990491,
      1625990491,
      1625990491,
      1625990491,
      1625990414,
      1625990414,
      1625989830,
      1625989828,
      1625989814,
      1625989811,
      1625989749,
      1626069642,
      1626069642,
      1626069642,
      1626069612,
      1626069612,
      1626069612,
      1626069612,
      1626069612,
      1626069612,
      1626069612,
      1626069612,
      1626069612,
      1626069612,
      1626069612,
      1626069612,
      1626069612,
      1626069613,
      1626069613,
      1626069612,
      1626069612,
      1626069612,
      1626069612,
      1626069612,
      1626069612,
      1626069612,
      1626069612,
      1626069612,
      1626069612,
      1626071270,
      1626066038,
      1626066036,
      1626066035,
      1626062643,
      1626062526,
      1626062494,
      1626062491,
      1626062484,
      1626062474,
      1626062473,
      1626062469,
      1626062465,
      1626062464,
      1626062413,
      1626062410,
      1626062404,
      1626062373,
      1626061899,
      1626061665,
      1626061665,
      1626061663,
      1626061663,
      1626061662,
      1626061662,
      1626061662,
      1626061660,
      1626061659,
      1626061659,
      1626061659,
      1626061659,
      1626061657,
      1626061656,
      1626061656,
      1626061656,
      1626061656,
      1626061654,
      1626061653,
      1626061653,
      1626061653,
      1626061653,
      1626061634,
      1626061634,
      1626061633,
      1626061633,
      1626061625,
      1626061625,
      1626061625,
      1626061625,
      1626061624,
      1626061622,
      1626061622,
      1626061622,
      1626061617,
      1626061617,
      1626061617,
      1626060700,
      1626059711,
      1626059532,
      1626059470,
      1626059411,
      1626058890,
      1626058854,
      1626058803,
      1626058748,
      1626056468,
      1626056110,
      1626055652,
      1626055652,
      1626055652,
      1626055345,
      1626055290,
      1626055219,
      1626052207,
      1626051965,
      1626051626,
      1626051613,
      1626051612,
      1626051612,
      1626051612,
      1626051612,
      1626051612,
      1626051611,
      1626051611,
      1626051611,
      1626051611,
      1626051611,
      1626051610,
      1626051610,
      1626051610,
      1626051610,
      1626051610,
      1626051610,
      1626051609,
      1626051609,
      1626051609,
      1626051609,
      1626051608,
      1626051608,
      1626051608,
      1626051608,
      1626051608,
      1626051608,
      1626051607,
      1626051607,
      1626051607,
      1626051607,
      1626051607,
      1626051606,
      1626051606,
      1626051606,
      1626051606,
      1626051606,
      1626051606,
      1626051605,
      1626051605,
      1626051605,
      1626051605,
      1626051605,
      1626051604,
      1626051604,
      1626051604,
      1626051604,
      1626051604,
      1626051604,
      1626051604,
      1626051604,
      1626051604,
      1626051603,
      1626051603,
      1626051603,
      1626051603,
      1626051603,
      1626051603,
      1626051603,
      1626051603,
      1626051602,
      1626048662,
      1626048662,
      1626048644,
      1626048602,
      1626048366,
      1626048362,
      1626048311,
      1626048310,
      1626048307,
      1626048307,
      1626048159,
      1626048107,
      1626048046,
      1626048040,
      1626048020,
      1626048008,
      1626048006,
      1626048003,
      1626048001,
      1626048000,
      1626048000,
      1626048000,
      1626048000,
      1626048000,
      1626048000,
      1626048000,
      1626047767,
      1626046322,
      1626046237,
      1626045686,
      1626044467,
      1626044467,
      1626044466,
      1626044456,
      1626044443,
      1626044409,
      1626044406,
      1626044405,
      1626044404,
      1626041857,
      1626041856,
      1626041856,
      1626041854,
      1626041403,
      1626041202,
      1626041194,
      1626041108,
      1626041095,
      1626041048,
      1626041013,
      1626041001,
      1626040977,
      1626040972,
      1626040966,
      1626040952,
      1626040944,
      1626040939,
      1626040932,
      1626040931,
      1626040928,
      1626040923,
      1626040922,
      1626040919,
      1626040915,
      1626040914,
      1626040909,
      1626040903,
      1626040895,
      1626040875,
      1626040868,
      1626040861,
      1626040859,
      1626040845,
      1626040835,
      1626040831,
      1626040825,
      1626040823,
      1626040821,
      1626040820,
      1626040820,
      1626040815,
      1626040814,
      1626040804,
      1626039399,
      1626038416,
      1626038416,
      1626038414,
      1626038402,
      1626037208,
      1626033607,
      1626030910,
      1626030581,
      1626030572,
      1626030545,
      1626030541,
      1626030539,
      1626030534,
      1626030514,
      1626030330,
      1626030310,
      1626030306,
      1626028203,
      1626026413,
      1626026408,
      1626026407,
      1626024049,
      1626023074,
      1626023043,
      1626022882,
      1626021045,
      1626020391,
      1626019203,
      1626014406,
      1626014229,
      1626013802,
      1626009945,
      1626009657,
      1626008828,
      1626008621,
      1626008532,
      1626008451,
      1626007266,
      1626004208,
      1626001837,
      1626001482,
      1626001246,
      1626001244,
      1626001208,
      1626001203,
      1625999408,
      1625997910,
      1625997730,
      1625997603,
      1625993168,
      1625991921,
      1625990491,
      1625990491,
      1625990414,
      1625989830,
      1626069642
    ]
  }
}